{
  "WatchFace_Info": {
    "DeviceName": "GTR 3 Pro",
    "WatchFaceId": 717972,
    "Preview": "Preview"
  },
  "ScreenNormal": {
    "Background": {
      "visible": true,
      "BackgroundImage": {
        "position": -1,
        "visible": true,
        "show_level": "ONLY_NORMAL",
        "x": 0,
        "y": 0,
        "w": 480,
        "h": 480,
        "src": "0002"
      }
    },
    "Elements": [
      {
        "elementName": "ElementStatuses",
        "visible": true,
        "Alarm": {
          "position": 2,
          "visible": true,
          "show_level": "ONLY_NORMAL",
          "x": 125,
          "y": 228,
          "src": "0159",
          "type": "Alarm"
        },
        "Bluetooth": {
          "position": 1,
          "visible": true,
          "show_level": "ONLY_NORMAL",
          "x": 90,
          "y": 228,
          "src": "0158",
          "type": "Bluetooth"
        }
      },
      {
        "elementName": "ElementBattery",
        "visible": true,
        "Number": {
          "position": 1,
          "visible": true,
          "align": "CENTER_H",
          "show_level": "",
          "imageX": 211,
          "imageY": 364,
          "space": 1,
          "zero": false,
          "img_First": "0023",
          "unit": "0033",
          "iconPosX": 0,
          "iconPosY": 0,
          "angle": 0,
          "follow": false,
          "unit_in_alignment": false
        }
      },
      {
        "elementName": "DateWeek",
        "visible": true,
        "Images": {
          "position": 1,
          "visible": true,
          "shortcut": false,
          "show_level": "ONLY_NORMAL",
          "X": 294,
          "Y": 233,
          "img_First": "0066",
          "image_length": 0
        }
      },
      {
        "elementName": "DateDay",
        "visible": true,
        "Number": {
          "position": 1,
          "visible": true,
          "align": "CENTER_H",
          "show_level": "ONLY_NORMAL",
          "imageX": 371,
          "imageY": 226,
          "space": -1,
          "zero": false,
          "img_First": "0006",
          "iconPosX": 0,
          "iconPosY": 0,
          "angle": 0,
          "follow": false,
          "unit_in_alignment": false,
          "type": "DAY"
        }
      },
      {
        "elementName": "AnalogTime",
        "visible": true,
        "show_level": "",
        "Second": {
          "position": 3,
          "visible": true,
          "show_level": "ONLY_NORMAL",
          "src": "0005",
          "center_x": 240,
          "center_y": 240,
          "pos_x": 28,
          "pos_y": 225,
          "start_angle": 0,
          "end_angle": 360,
          "cover_x": 0,
          "cover_y": 0,
          "scale_x": 0,
          "scale_y": 0
        },
        "Minute": {
          "position": 2,
          "visible": true,
          "show_level": "ONLY_NORMAL",
          "src": "0004",
          "center_x": 240,
          "center_y": 240,
          "pos_x": 33,
          "pos_y": 209,
          "start_angle": 0,
          "end_angle": 360,
          "cover_x": 0,
          "cover_y": 0,
          "scale_x": 0,
          "scale_y": 0
        },
        "Hour": {
          "position": 1,
          "visible": true,
          "show_level": "ONLY_NORMAL",
          "src": "0003",
          "center_x": 240,
          "center_y": 240,
          "pos_x": 27,
          "pos_y": 144,
          "start_angle": 0,
          "end_angle": 360,
          "cover_x": 0,
          "cover_y": 0,
          "scale_x": 0,
          "scale_y": 0
        }
      }
    ]
  },
  "ScreenAOD": {
    "Background": {
      "visible": true,
      "BackgroundImage": {
        "position": -1,
        "visible": true,
        "show_level": "ONLY_AOD",
        "x": 0,
        "y": 0,
        "w": 480,
        "h": 480,
        "src": "0002"
      }
    },
    "Elements": [
      {
        "elementName": "ElementStatuses",
        "visible": true,
        "Alarm": {
          "position": 2,
          "visible": true,
          "show_level": "ONLY_AOD",
          "x": 125,
          "y": 228,
          "src": "0159",
          "type": "Alarm"
        },
        "Bluetooth": {
          "position": 1,
          "visible": true,
          "show_level": "ONLY_AOD",
          "x": 90,
          "y": 228,
          "src": "0158",
          "type": "Bluetooth"
        }
      },
      {
        "elementName": "ElementBattery",
        "visible": true,
        "Number": {
          "position": 1,
          "visible": true,
          "align": "CENTER_H",
          "show_level": "",
          "imageX": 211,
          "imageY": 364,
          "space": 1,
          "zero": false,
          "img_First": "0023",
          "unit": "0033",
          "iconPosX": 0,
          "iconPosY": 0,
          "angle": 0,
          "follow": false,
          "unit_in_alignment": false
        }
      },
      {
        "elementName": "DateWeek",
        "visible": true,
        "Images": {
          "position": 1,
          "visible": true,
          "shortcut": false,
          "show_level": "ONLY_AOD",
          "X": 294,
          "Y": 233,
          "img_First": "0066",
          "image_length": 0
        }
      },
      {
        "elementName": "DateDay",
        "visible": true,
        "Number": {
          "position": 1,
          "visible": true,
          "align": "CENTER_H",
          "show_level": "ONLY_AOD",
          "imageX": 371,
          "imageY": 226,
          "space": -1,
          "zero": false,
          "img_First": "0006",
          "iconPosX": 0,
          "iconPosY": 0,
          "angle": 0,
          "follow": false,
          "unit_in_alignment": false,
          "type": "DAY"
        }
      },
      {
        "elementName": "AnalogTime",
        "visible": true,
        "show_level": "",
        "Second": {
          "position": 3,
          "visible": true,
          "show_level": "ONLY_AOD",
          "src": "0005",
          "center_x": 240,
          "center_y": 240,
          "pos_x": 29,
          "pos_y": 225,
          "start_angle": 0,
          "end_angle": 360,
          "cover_path": "AODblend",
          "cover_x": 0,
          "cover_y": 0,
          "scale_x": 0,
          "scale_y": 0
        },
        "Minute": {
          "position": 2,
          "visible": true,
          "show_level": "ONLY_AOD",
          "src": "0004",
          "center_x": 240,
          "center_y": 240,
          "pos_x": 33,
          "pos_y": 209,
          "start_angle": 0,
          "end_angle": 360,
          "cover_path": "AODblend",
          "cover_x": 0,
          "cover_y": 0,
          "scale_x": 0,
          "scale_y": 0
        },
        "Hour": {
          "position": 1,
          "visible": true,
          "show_level": "ONLY_AOD",
          "src": "0003",
          "center_x": 240,
          "center_y": 240,
          "pos_x": 27,
          "pos_y": 144,
          "start_angle": 0,
          "end_angle": 360,
          "cover_x": 0,
          "cover_y": 0,
          "scale_x": 0,
          "scale_y": 0
        }
      }
    ]
  },
  "Shortcuts": {
    "elementName": "ElementShortcuts",
    "visible": true,
    "Step": {
      "position": 5,
      "visible": true,
      "show_level": "ONLY_NORMAL",
      "x": 180,
      "y": 353,
      "w": 106,
      "h": 106,
      "src": "atajos",
      "type": "STEP"
    },
    "Heart": {
      "position": 4,
      "visible": true,
      "show_level": "ONLY_NORMAL",
      "x": 185,
      "y": 27,
      "w": 106,
      "h": 106,
      "src": "atajos",
      "type": "HEART"
    },
    "SPO2": {
      "position": 9,
      "visible": true,
      "show_level": "ONLY_NORMAL",
      "x": 55,
      "y": 300,
      "w": 100,
      "h": 100,
      "type": "SPO2"
    },
    "PAI": {
      "position": 3,
      "visible": true,
      "show_level": "ONLY_NORMAL",
      "x": 15,
      "y": 173,
      "w": 106,
      "h": 106,
      "src": "atajos",
      "type": "PAI_WEEKLY"
    },
    "Weather": {
      "position": 8,
      "visible": true,
      "show_level": "ONLY_NORMAL",
      "x": 65,
      "y": 55,
      "w": 100,
      "h": 100,
      "type": "WEATHER_CURRENT"
    },
    "Altimeter": {
      "position": 7,
      "visible": true,
      "show_level": "ONLY_NORMAL",
      "x": 305,
      "y": 300,
      "w": 100,
      "h": 100,
      "type": "ALTIMETER"
    },
    "Sunrise": {
      "position": 6,
      "visible": true,
      "show_level": "ONLY_NORMAL",
      "x": 310,
      "y": 55,
      "w": 100,
      "h": 100,
      "type": "SUN_CURRENT"
    },
    "Alarm": {
      "position": 2,
      "visible": true,
      "show_level": "ONLY_NORMAL",
      "x": 185,
      "y": 187,
      "w": 106,
      "h": 106,
      "src": "atajos",
      "type": "ALARM_CLOCK"
    },
    "Stopwatch": {
      "position": 1,
      "visible": true,
      "show_level": "ONLY_NORMAL",
      "x": 356,
      "y": 174,
      "w": 106,
      "h": 106,
      "src": "atajos",
      "type": "STOP_WATCH"
    }
  }
}